{
  "components": [
    {
      "type": "content",
      "container": "main",
      "components": [
        {
          "type": "heading",
          "name": "pageTitle",
          "size": "H1",
          "text": "Tbl Gn Address Book Types"
        },
        {
          "type": "row",
          "components": [
            {
              "type": "col",
              "class": "col-md-12",
              "components": [
                {
                  "icon": "add_circle_outline",
                  "name": "button0",
                  "style": {
                    "marginBottom": "10px"
                  },
                  "text": "Add",
                  "type": "button",
                  "events": {
                    "click": [
                      {
                        "path": "add-tbl-gn-address-book-type",
                        "type": "popup",
                        "then": [
                          {
                            "code": "grid0.Reload();",
                            "type": "execute"
                          },
                          {
                            "code": "await InvokeAsync(() => { StateHasChanged(); });",
                            "type": "execute"
                          }
                        ]
                      }
                    ]
                  }
                },
                {
                  "name": "grid0",
                  "allowFiltering": true,
                  "allowPaging": true,
                  "allowSorting": true,
                  "data": "${getTblGnAddressBookTypesResult}",
                  "events": {
                    "loadData": [],
                    "rowSelect": [
                      {
                        "parameters": [
                          {
                            "name": "AddressBookType_SEQ",
                            "value": "${event.AddressBookType_SEQ}"
                          }
                        ],
                        "path": "edit-tbl-gn-address-book-type",
                        "type": "popup",
                        "then": [
                          {
                            "code": "await InvokeAsync(() => { StateHasChanged(); });",
                            "type": "execute"
                          }
                        ]
                      }
                    ]
                  },
                  "title": "",
                  "columns": [
                    {
                      "property": "AddressBookType_SEQ",
                      "title": "Address Book Type SEQ"
                    },
                    {
                      "property": "AddressBookType_ID",
                      "title": "Address Book Type ID"
                    },
                    {
                      "property": "AddressBookTypeText",
                      "title": "Address Book Type Text"
                    },
                    {
                      "filterable": false,
                      "sortable": false,
                      "width": "70px",
                      "textAlign": "center",
                      "template": [
                        {
                          "attributes": [
                            {
                              "name": "@onclick:stopPropagation",
                              "value": true
                            }
                          ],
                          "buttonStyle": "danger",
                          "icon": "close",
                          "name": "gridDeleteButton",
                          "text": "",
                          "size": "sm",
                          "type": "button",
                          "events": {
                            "click": [
                              {
                                "error": [
                                  {
                                    "detail": "Unable to delete TblGnAddressBookType",
                                    "severity": "error",
                                    "summary": "Error",
                                    "type": "notify"
                                  }
                                ],
                                "name": "DB_At_VDC2.deleteTblGnAddressBookType",
                                "parameters": [
                                  {
                                    "name": "AddressBookType_SEQ",
                                    "value": "${data.AddressBookType_SEQ}"
                                  }
                                ],
                                "then": [
                                  {
                                    "code": "grid0.Reload();",
                                    "condition": "result != null",
                                    "type": "execute"
                                  }
                                ],
                                "type": "invoke"
                              }
                            ]
                          }
                        }
                      ]
                    }
                  ],
                  "type": "grid",
                  "itemType": "CanErp2.Models.DbAtVdc2.TblGnAddressBookType"
                }
              ]
            }
          ]
        }
      ]
    }
  ],
  "events": {
    "load": [
      {
        "name": "DB_At_VDC2.getTblGnAddressBookTypes",
        "parameters": [],
        "then": [
          {
            "name": "getTblGnAddressBookTypesResult",
            "type": "set",
            "value": "${result}",
            "valueType": "IEnumerable<CanErp2.Models.DbAtVdc2.TblGnAddressBookType>"
          }
        ],
        "type": "invoke"
      }
    ]
  },
  "name": "Tbl Gn Address Book Types",
  "layout": "Main"
}